feedfinder2.py
aio_feedfinder2-0.3.0.dist-info/DESCRIPTION.rst
aio_feedfinder2-0.3.0.dist-info/METADATA
aio_feedfinder2-0.3.0.dist-info/RECORD
aio_feedfinder2-0.3.0.dist-info/WHEEL
aio_feedfinder2-0.3.0.dist-info/metadata.json
aio_feedfinder2-0.3.0.dist-info/top_level.txt
