Metadata-Version: 2.0
Name: aio-feedfinder2
Version: 0.3.0
Summary: Find the feed URLs for a website.
Home-page: https://github.com/sergei-maertens/feedfinder2
Author: Sergei Maertens, Dan Foreman-Mackey
Author-email: sergeimaertens@gmail.com, foreman.mackey@gmail.com
License: MIT
Platform: UNKNOWN
Classifier: Programming Language :: Python :: 3.4
Classifier: Programming Language :: Python :: 3.5
Classifier: Development Status :: 4 - Beta
Classifier: Natural Language :: English
Classifier: Environment :: Web Environment
Classifier: Intended Audience :: Developers
Classifier: License :: OSI Approved :: MIT License
Classifier: Operating System :: OS Independent
Requires-Dist: aiohttp
Requires-Dist: beautifulsoup4
Requires-Dist: six
